{
    "id": 67,
    "name": "Diagnosis Code 12 Present On Admission",
    "description": "The present on admission (POA) indicator code associated with the diagnosis codes (principal and secondary).",
    "appliesTo": [
        "Inpatient"
    ],
    "suppliedIn": [
        "AB2D",
        "BB2",
        "BFD",
        "DPC",
        "SyntheticData"
    ],
    "bfdTableType": "CLAIM",
    "bfdColumnName": "clm_poa_ind_sw12",
    "bfdDbType": "CHAR",
    "bfdDbSize": 1,
    "bfdJavaFieldName": "diagnosis12PresentOnAdmissionCode",
    "ccwMapping": [
        "CLM_POA_IND_SW12"
    ],
    "cclfMapping": [],
    "fhirMapping": [
        {
            "version": "STU3",
            "resource": "ExplanationOfBenefit",
            "element": "diagnosis[N].extension[N].valueCoding.code",
            "fhirPath": "",
            "discriminator": [
                "diagnosis[N].extension[N].url = 'https://bluebutton.cms.gov/resources/variables/clm_poa_ind_sw12'",
                ""
            ],
            "additional": [
                "eob.diagnosis[N].extension[N].valueCoding.system = 'https://bluebutton.cms.gov/resources/variables/clm_poa_ind_sw12'",
                "eob.diagnosis[N].extension[N].valueCoding.display = {corresponding description from valueset specified in .system}",
                "eob.diagnosis[N].sequence = # selected by the code depending upon order of diagnosis'"
            ],
            "derived": "",
            "note": "The POA code correlates to the diagnosis code based upon the number. Ie 'Diagnosis Code 3 Present on Admission' relates to 'Diagnosis Code 3'.",
            "example": ""
        }
    ]
}
