{
    "id": 627,
    "name": "Medicare Coverage D End Date",
    "description": "That date that Medicare Coverage Part D ended for the Beneficiary.",
    "appliesTo": [
        "Part-D"
    ],
    "suppliedIn": [
        "BB2",
        "BCDA",
        "BFD",
        "DPC"
    ],
    "bfdTableType": "BENEFICIARIES",
    "bfdColumnName": "ptd_cvrg_end_dt",
    "bfdDbType": "DATE",
    "bfdDbSize": 8,
    "bfdJavaFieldName": "partDCoverageEndDate",
    "ccwMapping": [
        ""
    ],
    "cclfMapping": [],
    "fhirMapping": [
        {
            "version": "STU3",
            "resource": "",
            "element": "",
            "fhirPath": "",
            "discriminator": [],
            "additional": [],
            "derived": "",
            "note": "",
            "example": ""
        }
    ]
}
